crypton_tool/__init__.py
crypton_tool/cli.py
crypton_tool/crypton.py
crypton_tool/logger.py
crypton_tool-1.0.0.dist-info/entry_points.txt
crypton_tool-1.0.0.dist-info/LICENSE
crypton_tool-1.0.0.dist-info/WHEEL
crypton_tool-1.0.0.dist-info/METADATA
crypton_tool-1.0.0.dist-info/RECORD
