Metadata-Version: 2.1
Name: crypton-tool
Version: 1.0.0
Summary: Crypton Tool simple way to cryptography files and content
Home-page: https://github.com/msbar/crypton-tool
License: MIT
Author: Marciel Barcellos
Author-email: msbar2@gmail.com
Requires-Python: >=3.10,<4.0
Classifier: Development Status :: 1
Classifier: Intended Audience :: Developers
Classifier: Intended Audience :: Science/Research
Classifier: Intended Audience :: System Administrators
Classifier: License :: OSI Approved :: MIT License
Classifier: Programming Language :: Python :: 3
Classifier: Programming Language :: Python :: 3.10
Classifier: Programming Language :: Python :: 3.10
Classifier: Topic :: Cryptography
Requires-Dist: cryptography (>=38.0.1,<39.0.0)
Project-URL: Repository, https://github.com/msbar/crypton-tool
